README.md
setup.py
simple_gpg/__init__.py
simple_gpg/gpg.py
simple_gpg.egg-info/PKG-INFO
simple_gpg.egg-info/SOURCES.txt
simple_gpg.egg-info/dependency_links.txt
simple_gpg.egg-info/entry_points.txt
simple_gpg.egg-info/top_level.txt