Metadata-Version: 2.1
Name: simple-gpg
Version: 8.2
Summary: A simple program to make use of GNU Privacy Guard for Cryptographical use.
Home-page: https://github.com/Anish-M-code/simple-gpg
Author: Anish M
Author-email: aneesh25861@gmail.com
License: MIT License
Keywords: gnupg,openpgp,pgp,gpg,encryption,cryptography,student project
Platform: UNKNOWN
Classifier: Development Status :: 5 - Production/Stable
Classifier: Intended Audience :: Developers
Classifier: Topic :: Software Development
Classifier: License :: OSI Approved :: MIT License
Classifier: Programming Language :: Python :: 3
Classifier: Intended Audience :: Developers
Classifier: Intended Audience :: Education
Classifier: Intended Audience :: End Users/Desktop
Classifier: Topic :: Security :: Cryptography
